anticp2/__init__.py
anticp2/anticp2mod.py
AntiCP2-2.1.dist-info/LICENSE
AntiCP2-2.1.dist-info/METADATA
AntiCP2-2.1.dist-info/WHEEL
AntiCP2-2.1.dist-info/top_level.txt
AntiCP2-2.1.dist-info/RECORD
