Metadata-Version: 2.1
Name: AntiCP2
Version: 2.1
Summary: A package for calculating anticancer peptides
Home-page: https://webs.iiitd.edu.in/raghava/anticp2/
Author: Raghava Group
Author-email: raghavagps@gmail.com
License: UNKNOWN
Keywords: Prediction Anticancer Peptides
Platform: UNKNOWN
Classifier: Programming Language :: Python :: 3
Classifier: License :: OSI Approved :: MIT License
Classifier: Operating System :: OS Independent
Requires-Python: >=3.6
Requires-Dist: scikit-learn
